Metadata-Version: 2.4
Name: protomorph
Version: 0.1.2
Summary: Библиотека для работы с протоколом Protomorph от компании Galileosky
Author-email: "Дмитрий К." <development@galileosky.com>, "Семён К." <development@galileosky.com>
License-Expression: MIT
Project-URL: Homepage, https://galileosky.com
Project-URL: Repository, https://github.com/galileosky/protomorph
Project-URL: Documentation, https://github.com/galileosky/protomorph#readme
Project-URL: Bug Tracker, https://github.com/galileosky/protomorph/issues
Keywords: protomorph,protocol,serialization,network
Classifier: Development Status :: 3 - Alpha
Classifier: Intended Audience :: Developers
Classifier: Programming Language :: Python :: 3
Classifier: Programming Language :: Python :: 3.8
Classifier: Programming Language :: Python :: 3.9
Classifier: Programming Language :: Python :: 3.10
Classifier: Programming Language :: Python :: 3.11
Classifier: Topic :: Software Development :: Libraries :: Python Modules
Classifier: Topic :: System :: Networking
Requires-Python: >=3.8
Requires-Dist: nats-py>=2.6.0
Provides-Extra: dev
Requires-Dist: pytest>=7.4.3; extra == "dev"
Requires-Dist: pytest-asyncio>=0.21.1; extra == "dev"
Requires-Dist: black>=23.11.0; extra == "dev"
Requires-Dist: flake8>=6.1.0; extra == "dev"
Requires-Dist: mypy>=1.7.1; extra == "dev"
Provides-Extra: web
Requires-Dist: Flask>=3.0.0; extra == "web"
Requires-Dist: Flask-SocketIO>=5.3.6; extra == "web"
Requires-Dist: python-socketio>=5.8.0; extra == "web"
Requires-Dist: eventlet>=0.35.2; extra == "web"
